CHANGELOG
LICENSE
MANIFEST.in
README.markdown
RELEASE-VERSION
pavement.py
paver-minilib.zip
setup.py
version.py
dstat_interface/.DS_Store
dstat_interface/__init__.py
dstat_interface/main.py
dstat_interface.egg-info/PKG-INFO
dstat_interface.egg-info/SOURCES.txt
dstat_interface.egg-info/dependency_links.txt
dstat_interface.egg-info/requires.txt
dstat_interface.egg-info/top_level.txt
dstat_interface/core/.DS_Store
dstat_interface/core/__init__.py
dstat_interface/core/analysis.py
dstat_interface/core/dstat-interface.bat
dstat_interface/core/dstat.spec
dstat_interface/core/errors.py
dstat_interface/core/microdrop.py
dstat_interface/core/params.py
dstat_interface/core/plugin.py
dstat_interface/core/drivers/VirtualSerial.inf
dstat_interface/core/dstat/__init__.py
dstat_interface/core/dstat/boards.py
dstat_interface/core/dstat/comm.py
dstat_interface/core/dstat/dfu.py
dstat_interface/core/dstat/state.py
dstat_interface/core/experiments/__init__.py
dstat_interface/core/experiments/cal.py
dstat_interface/core/experiments/chronoamp.py
dstat_interface/core/experiments/cv.py
dstat_interface/core/experiments/experiment_loops.py
dstat_interface/core/experiments/experiment_template.py
dstat_interface/core/experiments/idle.py
dstat_interface/core/experiments/lsv.py
dstat_interface/core/experiments/pot.py
dstat_interface/core/experiments/swv.py
dstat_interface/core/interface/__init__.py
dstat_interface/core/interface/acv.glade
dstat_interface/core/interface/adc_pot.glade
dstat_interface/core/interface/adc_pot.py
dstat_interface/core/interface/analysis_options.glade
dstat_interface/core/interface/calib.glade
dstat_interface/core/interface/chronoamp.glade
dstat_interface/core/interface/cv.glade
dstat_interface/core/interface/data_view.py
dstat_interface/core/interface/db.glade
dstat_interface/core/interface/db.py
dstat_interface/core/interface/dpv.glade
dstat_interface/core/interface/dstatinterface.glade
dstat_interface/core/interface/exp_int.py
dstat_interface/core/interface/exp_window.py
dstat_interface/core/interface/hw_info.py
dstat_interface/core/interface/lsv.glade
dstat_interface/core/interface/pd.glade
dstat_interface/core/interface/plot.py
