Metadata-Version: 1.0
Name: dstat-interface
Version: 1.4.6
Summary: Interface software for DStat potentiostat.
Home-page: http://microfluidics.utoronto.ca/dstat
Author: Michael D. M Dryden
Author-email: mdryden@chem.utoronto.ca
License: GPLv3
Platform: UNKNOWN
